pyprusalink/__init__.py
pyprusalink/client.py
pyprusalink/types.py
pyprusalink/types_legacy.py
pyprusalink-2.1.1.dist-info/LICENSE
pyprusalink-2.1.1.dist-info/METADATA
pyprusalink-2.1.1.dist-info/WHEEL
pyprusalink-2.1.1.dist-info/top_level.txt
pyprusalink-2.1.1.dist-info/zip-safe
pyprusalink-2.1.1.dist-info/RECORD
